EasyPyQt/__init__.py
EasyPyQt/__main__.py
EasyPyQt/builder.py
EasyPyQt/constants.py
EasyPyQt/header.py
EasyPyQt/searthSignals.py
EasyPyQt/supportedSignals.py
EasyPyQt/utils.py
EasyPyQt-0.0.3.dist-info/METADATA
EasyPyQt-0.0.3.dist-info/RECORD
EasyPyQt-0.0.3.dist-info/WHEEL
EasyPyQt-0.0.3.dist-info/entry_points.txt
EasyPyQt-0.0.3.dist-info/top_level.txt
