Metadata-Version: 2.1
Name: EasyPyQt
Version: 0.0.3
Summary: A package for PyQt template&example codes
Home-page: UNKNOWN
Author: LeeFuuChang
Author-email: leefuuchang@gmail.com
License: LICENSE.md
Keywords: python,PyQt5
Platform: UNKNOWN
Classifier: Development Status :: 1 - Planning
Classifier: Intended Audience :: Developers
Classifier: Programming Language :: Python :: 3
Requires-Dist: PySide2
Requires-Dist: PyQt5
Requires-Dist: pyqt5-tools
